<annotation>
	<folder>collectedImages</folder>
	<filename>Yes (7).jpg</filename>
	<path>C:\Users\User\Downloads\RealTimeObjectDetection\Tensorflow\workspace\images\collectedImages\Yes (7).jpg</path>
	<source>
		<database>Unknown</database>
	</source>
	<size>
		<width>800</width>
		<height>600</height>
		<depth>3</depth>
	</size>
	<segmented>0</segmented>
	<object>
		<name>Yes</name>
		<pose>Unspecified</pose>
		<truncated>0</truncated>
		<difficult>0</difficult>
		<bndbox>
			<xmin>273</xmin>
			<ymin>224</ymin>
			<xmax>640</xmax>
			<ymax>542</ymax>
		</bndbox>
	</object>
</annotation>
